pydaraja/__init__.py
pydaraja/constants.py
pydaraja/exceptions.py
pydaraja/utils.py
pydaraja-1.0.0.dist-info/licenses/LICENSE
pydaraja-1.0.0.dist-info/METADATA
pydaraja-1.0.0.dist-info/WHEEL
pydaraja-1.0.0.dist-info/top_level.txt
pydaraja-1.0.0.dist-info/RECORD
