Metadata-Version: 2.4
Name: pydaraja
Version: 1.0.0
Summary: Python wrapper for Mpesa's Daraja API
Author-email: Raymond Kipkorir <hello@raykipkorir.com>
Maintainer-email: Raymond Kipkorir <hello@raykipkorir.com>
Project-URL: Homepage, https://github.com/raykipkorir/pydaraja
Project-URL: Bug Tracker, https://github.com/raykipkorir/pydaraja/issues
Keywords: mpesa,daraja
Classifier: Operating System :: OS Independent
Classifier: Programming Language :: Python :: 3
Classifier: Programming Language :: Python :: 3.12
Classifier: Programming Language :: Python :: 3.13
Classifier: Programming Language :: Python :: 3 :: Only
Requires-Python: >=3.12
License-File: LICENSE
Requires-Dist: requests>=2.31.0
Provides-Extra: dev
Requires-Dist: pre-commit~=3.7.0; extra == "dev"
Requires-Dist: black~=23.3.0; extra == "dev"
Requires-Dist: coverage~=7.6.0; extra == "dev"
Requires-Dist: pytest~=8.3.1; extra == "dev"
Requires-Dist: ruff~=0.11.12; extra == "dev"
Requires-Dist: pyright==1.1.401; extra == "dev"
Provides-Extra: ci
Requires-Dist: tox==4.34.1; extra == "ci"
Requires-Dist: tox-uv==1.29.0; extra == "ci"
Dynamic: license-file
